posit_keyring/__init__.py
posit_keyring/backends.py
posit_keyring/pkce.py
posit_keyring/token_file.py
posit_keyring-0.3.1.dist-info/licenses/LICENSE.txt
posit_keyring-0.3.1.dist-info/METADATA
posit_keyring-0.3.1.dist-info/WHEEL
posit_keyring-0.3.1.dist-info/entry_points.txt
posit_keyring-0.3.1.dist-info/top_level.txt
posit_keyring-0.3.1.dist-info/RECORD
