Metadata-Version: 2.4
Name: posit-keyring
Version: 0.3.1
Summary: A keyring backend for Posit Package Manager using OIDC device flow.
Author-email: Jacob Woliver <jacob.woliver@posit.co>
License-Expression: MIT
Project-URL: Homepage, https://github.com/posit-dev/posit-keyring
Project-URL: Repository, https://github.com/posit-dev/posit-keyring
Project-URL: Issues, https://github.com/posit-dev/posit-keyring/issues/
Classifier: Development Status :: 3 - Alpha
Classifier: Environment :: Console
Classifier: Intended Audience :: Developers
Classifier: Operating System :: OS Independent
Classifier: Programming Language :: Python :: 3.8
Classifier: Programming Language :: Python :: 3.9
Classifier: Programming Language :: Python :: 3.10
Classifier: Programming Language :: Python :: 3.11
Classifier: Programming Language :: Python :: 3.12
Classifier: Programming Language :: Python :: 3.13
Requires-Python: >=3.8
License-File: LICENSE.txt
Requires-Dist: keyring>=23.0.0
Requires-Dist: requests>=2.28.0
Requires-Dist: toml>=0.10.2
Dynamic: license-file
